passiter.py
passiter-0.0.7.dist-info/DESCRIPTION.rst
passiter-0.0.7.dist-info/WHEEL
passiter-0.0.7.dist-info/RECORD
passiter-0.0.7.dist-info/metadata.json
passiter-0.0.7.dist-info/METADATA
passiter-0.0.7.dist-info/top_level.txt
